Workbook

Sheet Legend & Instructions
A1: Personal Financial Strategic Plan — Toolkit
A2: Companion workbook to docs/Personal_Financial_Strategic_Plan.docx. Update the yellow cells; everything else recalculates automatically.
A4: Color legend
A5: Blue text | B5: A cell you fill in by hand (clients, monthly numbers, dates).
A6: Yellow fill | B6: A key assumption or input the model depends on — check these first.
A7: Green text | B7: A live link pulled from another sheet — don't overtype it.
A8: Black text | B8: A formula. Never hardcode over these; edit the input cells instead.
A10: What's in this workbook
A11: Dashboard | B11: Your single-glance snapshot: current numbers, milestone progress, client pipeline vs. plan targets.
A12: Monthly Tracker | B12: Log real income/expenses each month for 3 years. Feeds your actual net-worth trend.
A13: Accumulation Model | B13: The R$500k/R$1M timeline from the strategic plan, but live — it recalculates from your real numbers on the Dashboard instead of the plan's illustrative R$7,000/month, 9%/year example.
A14: Client & Retainer Tracker | B14: Every client/retainer with status, so your monthly recurring revenue is always known and feeds the Dashboard automatically.
A15: Action Checklist | B15: Every action item from the plan's Phase 5 (30/90-day/1yr/3yr goals) and the 5-point Master Enrichment Plan, with status tracking.
A17: Monthly routine (5 minutes)
A18: 1. Update Client & Retainer Tracker if anything changed (new client, lost client, status change).
A19: 2. Add this month's row to Monthly Tracker (revenue, expenses).
A20: 3. Update Dashboard's three input cells (current net worth, current MRR is automatic, current monthly savings).
A21: 4. Glance at Dashboard milestone table — Model Estimate updates itself.
A22: 5. Check off anything completed on the Action Checklist.

Sheet Dashboard
A1: Progress Dashboard
A2: Last updated: | B2: 2026-08-17
A4: Your current numbers (update monthly)
A5: Current net worth (R$) | B5: 0
A6: Current active monthly recurring revenue (R$) | B6: ='Client & Retainer Tracker'!B27
A7: Monthly amount you're investing/saving (R$) | B7: 0
A9: Milestone progress
A10: Milestone | B10: Target (R$) | C10: % complete | D10: Plan estimate (strategic plan doc) | E10: Model estimate (live, your numbers)
A11: R$10,000 | B11: 10000 | C11: =$B$5/B11 | D11: ~6–9 months | E11: ='Accumulation Model'!D14
A12: R$50,000 | B12: 50000 | C12: =$B$5/B12 | D12: ~Year 2 (18–24 mo) | E12: ='Accumulation Model'!D15
A13: R$100,000 | B13: 100000 | C13: =$B$5/B13 | D13: ~Year 3 | E13: ='Accumulation Model'!D16
A14: R$500,000 | B14: 500000 | C14: =$B$5/B14 | D14: ~Year 7 | E14: ='Accumulation Model'!D17
A15: R$1,000,000 | B15: 1000000 | C15: =$B$5/B15 | D15: ~Year 10 | E15: ='Accumulation Model'!D18
A17: Client pipeline vs. plan targets
A18: Metric | B18: Your number | C18: Plan target
A19: Active monthly recurring revenue | B19: ='Client & Retainer Tracker'!B27 | C19: R$4,500–10,000 by 90 days–1yr
A20: Active retainer clients | B20: ='Client & Retainer Tracker'!B28 | C20: 2–3 by 90 days
A21: Total active monthly revenue (all clients) | B21: ='Client & Retainer Tracker'!B29 | C21: R$8,000–10,000 by 1 year

Sheet Monthly Tracker
A1: Monthly Income & Net Worth Tracker (3 years)
A2: Fill in Revenue, Business expenses and Personal expenses each month (blue cells). Everything else calculates itself.
A4: Month | B4: Revenue (R$) | C4: Business expenses (R$) | D4: Personal expenses (R$) | E4: Net savings (R$) | F4: Cumulative net worth (R$) | G4: % to R$1M | H4: Notes
A5: Sep-2026 | B5: 0 | C5: 0 | D5: 0 | E5: =B5-C5-D5 | F5: =Dashboard!$B$5+E5 | G5: =F5/1000000
A6: Oct-2026 | B6: 0 | C6: 0 | D6: 0 | E6: =B6-C6-D6 | F6: =F5+E6 | G6: =F6/1000000
A7: Nov-2026 | B7: 0 | C7: 0 | D7: 0 | E7: =B7-C7-D7 | F7: =F6+E7 | G7: =F7/1000000
A8: Dec-2026 | B8: 0 | C8: 0 | D8: 0 | E8: =B8-C8-D8 | F8: =F7+E8 | G8: =F8/1000000
A9: Jan-2027 | B9: 0 | C9: 0 | D9: 0 | E9: =B9-C9-D9 | F9: =F8+E9 | G9: =F9/1000000
A10: Feb-2027 | B10: 0 | C10: 0 | D10: 0 | E10: =B10-C10-D10 | F10: =F9+E10 | G10: =F10/1000000
A11: Mar-2027 | B11: 0 | C11: 0 | D11: 0 | E11: =B11-C11-D11 | F11: =F10+E11 | G11: =F11/1000000
A12: Apr-2027 | B12: 0 | C12: 0 | D12: 0 | E12: =B12-C12-D12 | F12: =F11+E12 | G12: =F12/1000000
A13: May-2027 | B13: 0 | C13: 0 | D13: 0 | E13: =B13-C13-D13 | F13: =F12+E13 | G13: =F13/1000000
A14: Jun-2027 | B14: 0 | C14: 0 | D14: 0 | E14: =B14-C14-D14 | F14: =F13+E14 | G14: =F14/1000000
A15: Jul-2027 | B15: 0 | C15: 0 | D15: 0 | E15: =B15-C15-D15 | F15: =F14+E15 | G15: =F15/1000000
A16: Aug-2027 | B16: 0 | C16: 0 | D16: 0 | E16: =B16-C16-D16 | F16: =F15+E16 | G16: =F16/1000000
A17: Sep-2027 | B17: 0 | C17: 0 | D17: 0 | E17: =B17-C17-D17 | F17: =F16+E17 | G17: =F17/1000000
... A40: Aug-2029 | B40: 0 | C40: 0 | D40: 0 | E40: =B40-C40-D40 | F40: =F39+E40 | G40: =F40/1000000

Sheet Accumulation Model
A1: Accumulation Model (live)
A2: Same model as the strategic plan's Phase 3, but driven by your real Dashboard numbers instead of the plan's illustrative example.
A4: Assumptions
A5: Starting net worth (R$) | B5: =Dashboard!B5
A6: Monthly contribution (R$) | B6: =Dashboard!B7
A7: Annual return assumption | B7: 0.09
A9: Milestone timeline (recalculates from your numbers above)
A13: Milestone | B13: Target (R$) | C13: Month reached | D13: Years reached | E13: Plan estimate (strategic plan doc)
A14: R$10,000 | B14: 10000 | C14: =COUNTIF($B$22:$B$261,"<"&B14)+1 | D14: =C14/12 | E14: ~6–9 months
A15: R$50,000 | B15: 50000 | C15: =COUNTIF($B$22:$B$261,"<"&B15)+1 | D15: =C15/12 | E15: ~Year 2 (18–24 mo)
A16: R$100,000 | B16: 100000 | C16: =COUNTIF($B$22:$B$261,"<"&B16)+1 | D16: =C16/12 | E16: ~Year 3
A17: R$500,000 | B17: 500000 | C17: =COUNTIF($B$22:$B$261,"<"&B17)+1 | D17: =C17/12 | E17: ~Year 7
A18: R$1,000,000 | B18: 1000000 | C18: =COUNTIF($B$22:$B$261,"<"&B18)+1 | D18: =C18/12 | E18: ~Year 10
A20: 20-year monthly projection
A21: Month # | B21: Balance (R$)
A22: 1 | B22: =$B$5*(1+$B$7/12)+$B$6
A23: 2 | B23: =B22*(1+$B$7/12)+$B$6
A24: 3 | B24: =B23*(1+$B$7/12)+$B$6
A25: 4 | B25: =B24*(1+$B$7/12)+$B$6
A26: 5 | B26: =B25*(1+$B$7/12)+$B$6
A27: 6 | B27: =B26*(1+$B$7/12)+$B$6
A28: 7 | B28: =B27*(1+$B$7/12)+$B$6
A29: 8 | B29: =B28*(1+$B$7/12)+$B$6
A30: 9 | B30: =B29*(1+$B$7/12)+$B$6
A31: 10 | B31: =B30*(1+$B$7/12)+$B$6
A32: 11 | B32: =B31*(1+$B$7/12)+$B$6
A33: 12 | B33: =B32*(1+$B$7/12)+$B$6
A34: 13 | B34: =B33*(1+$B$7/12)+$B$6
... A261: 240 | B261: =B260*(1+$B$7/12)+$B$6

Sheet Client & Retainer Tracker
A1: Client & Retainer Tracker
A2: Every client feeding the Dashboard's revenue numbers. Delete the example row once you have real data.
A4: Client name | B4: Type | C4: Monthly value (R$) | D4: Status | E4: Start date | F4: Notes
A5: Example Client — Acme Co | B5: Retainer | C5: 1500 | D5: Active | E5: 2026-01-01 | F5: EXAMPLE ROW — delete or overwrite
A27: Total active retainer MRR (R$) | B27: =SUMIFS(C5:C25,B5:B25,"Retainer",D5:D25,"Active")
A28: Active retainer client count | B28: =COUNTIFS(B5:B25,"Retainer",D5:D25,"Active")
A29: Total active monthly revenue, all types (R$) | B29: =SUMIFS(C5:C25,D5:D25,"Active")

Sheet Action Checklist
A1: Action Checklist
A2: Sourced from the strategic plan's Phase 5 (implementation goals) and Master Enrichment Plan (top 5 priorities).
A4: # | B4: Horizon | C4: Action | D4: Target date | E4: Status | F4: Notes
A5: 1 | B5: This year | C5: Package your four skills into one clear, priced offer — stop selling hours, start selling outcomes. | E5: Not started
A6: 2 | B6: This year | C6: Convert at least 2 clients to retainers within 90 days — recurring revenue is the foundation everything else stands on. | E6: Not started
A7: 3 | B7: This year | C7: Build a 3-month emergency fund before investing a single real elsewhere. | E7: Not started
A8: 4 | B8: This year | C8: Once stable, automate monthly investing into a diversified, low-fee portfolio — consistency matters more than timing. | E8: Not started
A9: 5 | B9: This year | C9: Delegate execution work as revenue allows, so your time shifts toward strategy and relationships. | E9: Not started
A10: 6 | B10: 30-day | C10: Revenue: land or renew 2 clients at a rate 20% above your current average. | E10: Not started
A11: 7 | B11: 30-day | C11: Profit: bank the first R$1,000 toward your emergency fund. | E11: Not started
A12: 8 | B12: 30-day | C12: Heritage: define your niche and offer in one sentence you can say confidently. | E12: Not started
A13: 9 | B13: 30-day | C13: Investment: none yet — capital stays liquid. | E13: Not started
A14: 10 | B14: 90-day | C14: Revenue: R$4,500–6,000/month recurring or predictable (2–3x current). | E14: Not started
A15: 11 | B15: 90-day | C15: Profit: 3-month emergency fund roughly in place. | E15: Not started
A16: 12 | B16: 90-day | C16: Heritage: a simple portfolio site and one consistent content/outreach channel running. | E16: Not started
... A25: 21 | B25: 3-year | C25: Investment: diversified portfolio in place; on track toward the R$500k milestone within another 3–5 years. | E25: Not started
